gdmec23120351/__init__.py
gdmec23120351-0.1.2.dist-info/METADATA
gdmec23120351-0.1.2.dist-info/WHEEL
gdmec23120351-0.1.2.dist-info/entry_points.txt
gdmec23120351-0.1.2.dist-info/RECORD
