Metadata-Version: 2.4
Name: gdmec23120351
Version: 0.1.2
Summary: Add your description here
Requires-Python: >=3.11
Requires-Dist: mcp[cli]>=1.9.4
